stingconf/__init__.py
stingconf/config.py
stingconf/parser.py
stingconf/utils.py
stingconf-0.0.3.dist-info/LICENSE
stingconf-0.0.3.dist-info/METADATA
stingconf-0.0.3.dist-info/WHEEL
stingconf-0.0.3.dist-info/top_level.txt
stingconf-0.0.3.dist-info/RECORD
