Metadata-Version: 2.1
Name: stingconf
Version: 0.0.3
Summary: Layered configuration library
Home-page: https://github.com/rsp9u/stingconf
Author: 
Author-email: 
Maintainer: rsp9u
Maintainer-email: gctwt852@yahoo.co.jp
License: MIT
Platform: UNKNOWN
Classifier: License :: OSI Approved :: MIT License
Classifier: Operating System :: OS Independent
Classifier: Programming Language :: Python
Classifier: Programming Language :: Python :: 2
Classifier: Programming Language :: Python :: 2.7
Classifier: Programming Language :: Python :: 3
Classifier: Programming Language :: Python :: 3.7
Requires-Dist: PyYAML
